pyOP/SKLearnInterface.py
pyOP/optimization.py
pyOP/Evolution/Evolution.py
pyOP/Fitness/FitnessFunction.py
pyOP/Nodes/BaseNode.py
pyOP/Nodes/SymbolicRegressionNodes.py
pyOP/Selection/Selection.py
pyOP/Variation/Variation.py
pymhopt-0.0.2.data/scripts/pymhopt_package
pymhopt-0.0.2.dist-info/METADATA
pymhopt-0.0.2.dist-info/RECORD
pymhopt-0.0.2.dist-info/WHEEL
pymhopt-0.0.2.dist-info/top_level.txt
