Metadata-Version: 2.1
Name: pymhopt
Version: 0.0.2
Summary: Python Wrapper for Optimization Algorithms
Home-page: https://github.com/ajayarunachalam/pymhopt/
Author: Ajay Arunachalam
Author-email: ajay.arunachalam08@gmail.com
License: UNKNOWN
Platform: UNKNOWN
Classifier: Programming Language :: Python :: 3
Classifier: License :: OSI Approved :: MIT License
Classifier: Operating System :: OS Independent
Requires-Dist: pandas
Requires-Dist: numpy
Requires-Dist: gplearn
Requires-Dist: scikit-learn
Requires-Dist: matplotlib
Requires-Dist: graphviz
